htmlpull/__main__.py
htmlpull/cli.py
htmlpull-0.3.0.dist-info/entry_points.txt
htmlpull-0.3.0.dist-info/WHEEL
htmlpull-0.3.0.dist-info/METADATA
htmlpull-0.3.0.dist-info/RECORD
